pyutx/__init__.py
pyutx/errors.py
pyutx/types.py
pyutx/api/__init__.py
pyutx/api/async_support/__init__.py
pyutx/api/async_support/binance.py
pyutx/api/async_support/bingx.py
pyutx/api/async_support/bybit.py
pyutx/api/async_support/clients.py
pyutx/api/async_support/okx.py
pyutx-0.2.2.dist-info/METADATA
pyutx-0.2.2.dist-info/WHEEL
pyutx-0.2.2.dist-info/licenses/LICENSE
pyutx-0.2.2.dist-info/RECORD
