Metadata-Version: 2.4
Name: pyutx
Version: 0.2.2
Summary: Unified Trading eXecution
Project-URL: Homepage, https://github.com/dothanhlongtld/pyutx.git
Project-URL: Issues, https://github.com/dothanhlongtld/pyutx.git
Author-email: Long Do <dothanhlongtld@gmail.com>
License-File: LICENSE
Classifier: License :: OSI Approved :: MIT License
Classifier: Operating System :: OS Independent
Classifier: Programming Language :: Python :: 3
Requires-Python: >=3.0
Requires-Dist: httpx>=0.28.1
